{
  "file_name":"tmpy9nfmms3_压缩_水印测试_p2.png",
  "file_type":"contract",
  "raw_summary":"五、本合同发生的争议，由双方当事人协商解决协商或遇解不成的，依法向当地人民\n法院起诉。\n六、本合同一式二份，买方一份，卖方一份 本合同在双方签字或盖章后生效\n七、其它约定；\n甲方（公章）： 乙方（公章）\n测试水白\n法定代表人（签字）： 法定代表人（签字）\n年\n测试水 附件\n测试水印\n测试水印\n侧试水印\n式水印",
  "corrected_content":"五、本合同发生的争议，由双方当事人协商解决；协商不成的，依法向当地人民法院起诉。\n六、本合同一式二份，买方执一份，卖方执一份。本合同自双方签字或盖章后生效。\n七、其它约定：\n甲方（公章）：\n法定代表人（签字）：\n年  月  日\n乙方（公章）：\n法定代表人（签字）：\n年  月  日\n（以下为附件区域）",
  "risks":[
    "争议解决条款中“协商或遇解不成”存在明显错别字（“遇解”应为“协商”或“调解”），可能导致条款效力争议。",
    "签字盖章部分格式混乱，未留出填写日期、法定代表人姓名的明确位置，存在签署效力风险。",
    "“其它约定”条款为空白，未明确任何补充约定，可能产生未尽事宜的争议。",
    "合同份数分配表述不完整（“买方一份，卖方一份”建议明确为“各方执一份”或“各持一份”）。",
    "附件部分仅以“测试水印”等占位文字呈现，未列明附件具体内容，存在合同内容不完整的风险。"
  ],
  "safety_score":95.0,
  "suggestion":"",
  "similarity":0.7409836066
}